HISTORY.rst
LICENSE
MANIFEST.in
README.rst
setup.py
pyramid_rawes/__init__.py
pyramid_rawes.egg-info/PKG-INFO
pyramid_rawes.egg-info/SOURCES.txt
pyramid_rawes.egg-info/dependency_links.txt
pyramid_rawes.egg-info/not-zip-safe
pyramid_rawes.egg-info/requires.txt
pyramid_rawes.egg-info/top_level.txt
tests/__init__.py
tests/fixtures.py
tests/test_general.py