Metadata-Version: 1.1
Name: pyramid-rawes
Version: 0.5.0
Summary: Rawes bindings for pyramid
Home-page: https://github.com/koenedaele/pyramid_rawes
Author: Koen Van Daele
Author-email: koen_van_daele@telenet.be
License: MIT
Keywords: pyramid elastic search rawes
Platform: UNKNOWN
Classifier: Intended Audience :: Developers
Classifier: Development Status :: 4 - Beta
Classifier: License :: OSI Approved :: MIT License
Classifier: Programming Language :: Python
Classifier: Programming Language :: Python :: 2.7
Classifier: Programming Language :: Python :: 3.2
Classifier: Programming Language :: Python :: 3.3
Classifier: Framework :: Pyramid
Classifier: Topic :: Internet :: WWW/HTTP :: Indexing/Search
